Metadata-Version: 2.1
Name: routeros-updates
Version: 0.2.2
Summary: RouterOS Update Checker and Downloader
Home-page: https://github.com/phistrom/routeros-updates
Author: Phillip Stromberg
Author-email: phillip@strombergs.com
License: MIT
Platform: UNKNOWN
Classifier: Development Status :: 5 - Production/Stable
Classifier: Intended Audience :: System Administrators
Classifier: Natural Language :: English
Classifier: License :: OSI Approved :: MIT License
Classifier: Programming Language :: Python
Classifier: Programming Language :: Python :: 2
Classifier: Programming Language :: Python :: 2.7
Classifier: Programming Language :: Python :: 3
Classifier: Programming Language :: Python :: 3.5
Classifier: Programming Language :: Python :: 3.6
Classifier: Programming Language :: Python :: 3.7
